{"id":"1029","title":"Softwareentwickler \/ -in im Consultingumfeld","description":"Wir unterst\u00fctzen als unabh\u00e4ngiger IT-Dienstleister Firmen bei der Realisierung von Projekten im SAP-Bereich. Zu unseren Kunden geh\u00f6ren internationale Unternehmen der chemisch-pharmazeutischen Industrie sowie der Stahl- und Automobil(zuliefer)industrie wie beispielsweise die Bayer AG, die Boehringer Ingelheim Pharma GmbH & Co. KG, die Springer Science & Business Media GmbH, die Salzgitter AG.\r\n\r\nUm unser Wachstum weiter voran zu treiben suchen wir zur Festeinstellung den\/die engagierten *Softwareentwickler \/ - in im Consultingumfeld*\r\n\r\n*Ihre Aufgaben:*\r\n\u2022 Realisierung anspruchsvoller Projekte auf Basis der betrieblichen Softwarel\u00f6sung SAP\r\n\u2022 Customizing und Programmierung unter Ber\u00fccksichtigung der kundenspezifischen Gesch\u00e4ftsumgebung\r\n\u2022 Plattform\u00fcbergreifende Integration diverser IT-Anwendungen\r\n\u2022 Intensive Kommunikation und enge Zusammenarbeit mit den Kunden und deren\r\nProjektpartnern\r\n\u2022 Betreuung unserer Kunden und der Anwendungen (Wartung, Support und Schulung)\r\n\r\n*Ihr Profil:*\r\n\u2022 Sie sind Hochschulabsolvent und haben Ihr Studium der (Wirtschafts-) Informatik, Mathematik, Ingenieurwissenschaften, Betriebswirtschaftslehre oder einer technischnaturwissenschaftlichen Fachrichtung erfolgreich abgeschlossen\r\n\u2022 Alternativ verf\u00fcgen Sie \u00fcber Berufserfahrungen im IT-Umfeld, idealerweise in den Bereichen der SAP Technologie oder SAP Business Solution\r\n\u2022 Sie verf\u00fcgen \u00fcber gute Kenntnisse in der Softwareentwicklung und beherrschen mindestens eine Programmiersprache (Java, C\/C++, PHP, ABAP o. \u00e4.)\r\n\u2022 Sie haben Spa\u00df an Herausforderungen und Interesse an neuen Technologien\r\n\u2022 Gutes Verst\u00e4ndnis betriebswirtschaftlicher Prozesse ist von Vorteil\r\n\u2022 Sie haben Fremdsprachenkenntnisse, idealerweise gute Englischkenntnisse in Wort und Schrift\r\n\u2022 Sie denken analytisch, sind flexibel, teamf\u00e4hig und arbeiten kunden- sowie l\u00f6sungsorientiert\r\n\u2022 Sie sind zu \u00fcberregionaler Reiset\u00e4tigkeit bereit\r\n\r\n*Unser Angebot:*\r\n\u2022 Attraktive Einstiegsm\u00f6glichkeit in ein junges, innovatives und internationales Team\r\n\u2022 Individuelles Einarbeitungsprogramm in das SAP-Umfeld.\r\n\u2022 Herausfordernde Aufgaben in anspruchsvollen Projekten in einem internationalen Arbeitsumfeld.\r\n\u2022 Sehr gute pers\u00f6nliche und berufliche Entwicklungsm\u00f6glichkeiten in einem\r\nwachstumsorientierten Unternehmen.\r\n\u2022 Lukratives Festgehalt mit attraktiven Zusatzleistungen wie Erfolgsbeteiligungen, Weiterbildungsm\u00f6glichkeiten, Firmenwagen nach erfolgreich bestandener Probezeit und T\u00e4tigkeitserfordernis.\r\n","how_to_apply":"Bitte senden Sie Ihre vollst\u00e4ndigen Bewerbungsunterlagen an\r\nInformatik DV GmbH Ihre Ansprechpartnerin ist:\r\nCarolastra\u00dfe 7a Frau D\u00f6rte Wahn-Neubert\r\n09111 Chemnitz E-Mail: doerte.wahn-neubert@informatik-dv.de\r\nTel.: 0371 40079-0 Tel.: 0371 40079-17\r\nStand: April 2011 www.informatik-dv.de\r\n\r\nGern nehmen wir Ihre Bewerbung per E-Mail entgegen.","company":"Informatik DV GmbH","company_homepage":"http:\/\/www.informatik-dv.de","zipcode":"09111","city":"Chemnitz","state":"bundesweit","country":"","job_version":"3","expiration_date":"09.06.2011","expiration_date_ts":"1307570400","date_added":"28.04.2011","date_added_ts":"1303981709","view_count":"14","attachment":"http:\/\/wwwdup.uni-leipzig.de\/jobportal\/job\/download\/1029.pdf"}