{"id":"175","title":"Web Application Developer Java\/PHP (m\/w)","description":"Spreadshirt hat sich seit seiner Gr\u00fcndung 2002 von einem der erfolgreichsten Start-Ups in Deutschlands zur f\u00fchrenden Social-Commerce-Plattform f\u00fcr Bekleidung in Europa und der Nummer drei in den USA entwickelt. Wir bedienen heute weltweit mehrere Millionen von Partnern und Kunden in 14 L\u00e4ndern und 11 Sprachen.\r\nAb sofort suchen wir einen ...\r\n\r\n*Web Application Developer Java\/PHP (m\/w)*\r\n\r\nAls Web Application Developer erwarten Dich bei Spreadshirt spannende Aufgaben weitab von Standard-eCommerce-L\u00f6sungen. Die Spreadshirt-Plattform ist ein au\u00dfergew\u00f6hnlich vielseitiges System und stellt vielf\u00e4ltige Herausforderungen an Software-Architektur und -Entwicklung. Zu den technologisch und inhaltlich spannendsten Themen geh\u00f6ren \r\n\u2022\tWandel von einem monolithischen PHP-System zu einer Komponenten-basierten J2EE-Architektur,\r\n\u2022\tWeiterentwicklung der Spreadshirt API,\r\n\u2022\tTechnologische Modernisierung bestehender Web-Anwendungen (z.B. HTML 5, Ajax mit jQuery, Java Web-Frameworks, RIA, CMS-Anbindung),\r\n\u2022\tSkalierbarkeit und Performance (z.B. Clustering, Caching, Replikation, Query-Optimierung),\r\n\u2022\tStrategische Technologieplanung: Evaluierung und Prototyping im Umfeld von Android-, iPhone\/iPad-Applikationen, 3D-Grafik, GWT und anderen Frameworks.\r\n\r\n*Deine Aufgaben im Detail*\r\n\u2022\tServerseitige Programmierung von Web-Anwendungen in PHP und\/oder Java,\r\n\u2022\tClientseitige Programmierung in Javascript,\r\n\u2022\tBeratung bei der Projektplanung vor dem Hintergrund von Usability und technischen M\u00f6glichkeiten,\r\n\u2022\tAktive Beteiligung an der strategischen Technologieplanung,\r\n\u2022\tSpa\u00df an der Arbeit haben und andere dazu befl\u00fcgeln.\r\n\r\n*Dein Profil*\r\n\u2022\tDu hast ein abgeschlossenes Studium der Informatik oder einschl\u00e4gige Erfahrung im Bereich Web-Entwicklung.\r\n\u2022\tDu hast hervorragende Kenntnisse in Java oder PHP oder einer anderen Programmiersprache.\r\n\u2022\tDu beherrschst die Konzepte der Plattform Web und die g\u00e4ngigen Frontend-Technologien (XHTML, CSS, Javascript).\r\n\u2022\tDu hast ein Herz f\u00fcr Benutzer und ein gutes Gesp\u00fcr f\u00fcr Usability.\r\n\u2022\tDu hast ein ausgepr\u00e4gtes Interesse an innovativen Technologien und Spa\u00df daran, sie l\u00f6sungsorientiert einzusetzen.\r\n\u2022\tWir erwarten keinen Oxford-Standard, Du bist jedoch in der Lage, Dich fl\u00fcssig auf Englisch mit Kollegen zu verst\u00e4ndigen.\r\n\r\n*Wir bieten Dir*\r\n\u2022\tWeitreichende Verantwortung f\u00fcr entscheidende Teile der Spreadshirt-Plattform.\r\n\u2022\tEine unkonventionelle und gleichzeitig professionelle Arbeitsatmosph\u00e4re mit viel Freiraum f\u00fcr neue Ideen.\r\n\u2022\tZusammenarbeit mit sympathischen und professionellen Teams in flachen Hierarchien.\r\n\u2022\tDie M\u00f6glichkeit, Dich st\u00e4ndig nach Deinen eigenen Interessen fachlich weiterzuentwickeln.","how_to_apply":"Wir freuen uns \u00fcber Deine vollst\u00e4ndigen Bewerbungsunterlagen unter Angabe der Referenznummer X01-I34, Deines fr\u00fchestm\u00f6glichen Eintrittstermins und Deinen Gehaltsvorstellungen bevorzugt per E-Mail an jobs@spreadshirt.net. F\u00fcr R\u00fcckfragen steht Dir Karen Arnold gern zur Verf\u00fcgung. \r\n\r\n","company":"sprd.net AG (Spreadshirt)","company_homepage":"http:\/\/www.spreadshirt.de","zipcode":"04229","city":"Leipzig","state":"Sachsen","country":"Deutschland","job_version":"1","expiration_date":"27.01.2011","expiration_date_ts":"1296082800","date_added":"16.12.2010","date_added_ts":"1292508477","view_count":"14","attachment":"http:\/\/wwwdup.uni-leipzig.de\/jobportal\/job\/download\/175.pdf"}