{"id":"285","title":"Praktikum im Bereich Online-Redaktion \/  Content-Management  \/ Web-Design (w\/m) bei der Ruder-Bundesliga","description":"*WER WIR SIND*\r\nDie Ruder-Event GmbH (REG) ist die aufstrebende Sportagentur in der Vermarktung des Rudersports in Deutschland. Als junge, zukunftsorientierte Agentur geht die REG in der Traditionssportart Rudern neue Wege und begreift sich als Innovationsmotor, dessen Ziel die Verbindung von Tradition und Moderne ist.\r\n\r\n*WAS WIR MACHEN*\r\nIm Jahr 2009 mit der neuen Rennserie Ruder-Bundesliga gestartet, deckt die REG heute alle Felder des modernen Eventmanagements ab. So steht neben der Konzeption, Organisation und Durchf\u00fchrung von Veranstaltungen auch die Presse- und Medienarbeit auf der Agenda. Ziel der REG ist eine publikums- und medienwirksame Pr\u00e4sentation des Rudersports in der \u00d6ffentlichkeit. \r\nSeit 2010 engagiert sich die REG auch in der Vermarktung der deutschen U19-Junioren-Nationalmannschaft.\r\n\r\n*WAS SIND DEINE AUFGABEN*\r\n* redaktionelle Aufbereitung der Ruder-Bundesliga\r\n* organisatorische Eigenverantwortung eines Teilbereichs\r\n* Pfege unternehmenseigener Daten\r\n* Zusammenarbeit mit abteilungs\u00fcbergreifenden Teams\r\n* Beschafung und Archivierung von Sendematerial und Presseartikeln\r\n* Vorbereitung von Pressemitteilungen und Berichten\r\n* Bildbearbeitung\r\n\r\n*WAS DU MITBRINGEN SOLLTEST*\r\n* Studium im Bereich Medienwissenschaften, Medienwirtschaft, Medientechnik, Medieninformatik oder vergleichbarer Studiengang\r\n* hohes Verantwortungsbewusstsein und gro\u00dfe Zuverl\u00e4ssigkeit\r\n* Affinit\u00e4t zum Sport\r\n* Kenntnisse in der Programmserie von Adobe (Photoshop, Illustrator, Indesign, Lightroom)\r\n* Kenntnisse im Content-Management-System Typo 3\r\n* technisches Grundverst\u00e4ndnis im Online-Bereich\r\n* hohe Internet-, Film- und TV-Afnit\u00e4t\r\n\r\n*WAS WIR BIETEN*\r\n* spannende und herausfordernde Aufgaben in einem jungen, dynamischen Team mit fachen Hierarchien und viel Platz f\u00fcr eigene Ideen\r\n* eigenverantwortliches Arbeiten\r\n* einen unschlagbaren Blick \u00fcber die Stadt Hannover von unserer Dachterrasse\r\n* gew\u00fcnschter Eintrittstermin nach Vereinbarung\r\n* verg\u00fctetes Praktikum","how_to_apply":"ANSPRECHPARTNER:\r\n\r\nArne Simann\r\nMobil: 0163 - 700 00 95\r\nEmail: arne.simann@ruder-bundesliga.de\r\n\r\nRuder-Event GmbH\r\nEscherstr. 14\r\n30159 Hannover\r\nFax: 0511 - 35 34 20 97\r\n\r\nBewerbungen k\u00f6nnen per Mail, Fax oder auf dem Postweg eingereicht werden.","company":"Ruder-Event GmbH","company_homepage":"http:\/\/www.ruder-bundelsiga.de","zipcode":"30159","city":"Hannover","state":"Niedersachsen","country":"Deutschland","job_version":"1","expiration_date":"18.02.2011","expiration_date_ts":"1297983600","date_added":"07.01.2011","date_added_ts":"1294401679","view_count":"21","attachment":"http:\/\/wwwdup.uni-leipzig.de\/jobportal\/job\/download\/285.pdf"}