{"id":"305","title":"Financial Trainee bei der OVB","description":"Ich suche zur Erweiterung und Betreuung  meines Kundenkreises junge aufgeschlossene Mitarbeiter.\r\n\r\nDer Aufgabenbereich umfasst die Aquisition neuer Kunden, die Analyse bestehender finanz. Verbindlichkeiten, sowie die Betreuung und den Service f\u00fcr meine Bestandskunden.\r\n\r\nIch biete eine fachkundige Einweisung und Ausbildung, sowie eine sichere und langfristige Betreuung ohne eigene finanz. Verbindlichkeiten.\r\n\r\nHabe ich Ihr Interesse geweckt ? \r\n\r\nSie sind bereit f\u00fcr eine neue nebenberufliche Herausforderung!\r\n\r\nDie Entscheidung ist gefallen. F\u00fcr einen begehrten Job mit enormen Zukunftsperspektiven. F\u00fcr ein Team, deren Erfolg Sie durch Ihren Ehrgeiz und Engagement ma\u00dfgeblich beeinflussen. \r\n\r\nUnd doch sind Sie bei der OVB Ihr eigener Chef und haben so die Chance, mit Unterst\u00fctzung Ihres Teams, Ihre eigenen Ziele zu verwirklichen. \r\n\r\nDie H\u00f6he Ihres Einkommens bestimmen Sie selbst. Entweder bei freier Zeiteinteilung durch eine nebenberufliche T\u00e4tigkeit oder als Vollzeitt\u00e4tigkeit in der Beratung Ihrer Kunden bis hin zum Management.\r\n\r\nDas erste Ziel: Entwickeln Sie sich vom Teammitglied zum Teamleader!\r\n\r\nIch brauchen Sie. Mit klugem Kopf und vollem Einsatz.\r\n\r\nIch freue mich auf Ihre Bewerbung","how_to_apply":"F\u00fcr eine erste Verbindungsaufnahme bitte die tel. Erreichbarkeit sicher stellen. Ein Bewerbungsgespr\u00e4ch erfolgt nach Terminabsprache.\r\n\r\nUndine Libossek\r\n03493 978 946 8\r\n\r\noder \r\n\r\nundine.libossek@online.de","company":"Undine Libossek Financial Advisor f\u00fcr die OVB","company_homepage":"http:\/\/www.undine-libossek.ovb.de","zipcode":"06749","city":"Bitterfeld","state":"Sachsen- Anhalt","country":"Deutschland","job_version":"1","expiration_date":"22.02.2011","expiration_date_ts":"1298329200","date_added":"12.01.2011","date_added_ts":"1294818743","view_count":"16"}