{"id":"396","title":"Volont\u00e4r Business Development (m\/w)","description":"*Was dich erwartet:*\r\n\r\n* Mitwirkung bei strategischen und operativen Projekten in allen relevanten Bereichen des Unternehmens\r\n* Vorbereitung und Durchf\u00fchrung von Markt- und Wettbewerbsanalysen\r\n* Analyse und Planung von neuen Gesch\u00e4ftsmodellen\r\n* Definition von neuen Funktionalit\u00e4ten und Optimierung von Prozessen\r\n* Suchmaschinenoptimierung und -marketing \r\n* Eigenst\u00e4ndige Durchf\u00fchrung von Projekten\r\n\r\n\r\n*Folgende Anforderungen haben wir:*\r\n\r\n* Studium mit sehr guten Noten in Geistes-, Betriebswirtschafts- und Kommunikationswissenschaften oder einem vergleichbaren Studiengang\r\n* Ausgepr\u00e4gte Kommunikationsf\u00e4higkeit\r\n* Unternehmerisches Denken und Handeln\r\n* Ausgepr\u00e4gte Internetaffinit\u00e4t und Kenntnisse im Umgang mit MS Office\r\n* Idealerweise Grundkenntnisse in der Suchmaschinenoptimierung sowie der Gestaltung von Websites\r\n* Teamf\u00e4higkeit, Eigeninitiative, Zuverl\u00e4ssigkeit\r\n* Perfekte Deutsch- und gute Englischkenntnisse\r\n\r\n\r\nW\u00e4hrend des zw\u00f6lfmonatigen Volontariats arbeiten Sie eigenverantwortlich und verwirklichen innovative Konzepte innerhalb unserer Gesellschaft. Zus\u00e4tzlich werden Sie individuell von unseren Mitarbeiter betreut und durch Projektarbeit sowie Vortr\u00e4ge und Workshops in Ihrer beruflichen Weiterentwicklung gef\u00f6rdert. Dar\u00fcber hinaus arbeiten Sie mit einem netten, motivierten Team in einer der sch\u00f6nsten Lagen von Hamburg in direkter Alstern\u00e4he.","how_to_apply":"Bei Interesse senden Sie uns Ihre aussagekr\u00e4ftigen Bewerbungsunterlagen unter Angabe Ihres fr\u00fchestm\u00f6glichen Eintrittstermins an die angegebene E-Mail-Adresse.\r\n\r\n\r\nIhre Ansprechpartnerin:\r\nICS Internet Consumer Services GmbH\r\nElisa Felske\r\nHeimhuder Str. 72\r\n20148 Hamburg\r\nE-Mail-Adresse: personal@internetconsumerservices.com\r\nWeb: www.internetconsumerservices.com","company":"ICS Internetconsumerservices GmbH","company_homepage":"http:\/\/www.internetconsumerservices.com","zipcode":"20148","city":"Hamburg","state":"Hamburg","country":"Deutschland","job_version":"1","expiration_date":"01.05.2011","expiration_date_ts":"1304200800","date_added":"24.01.2011","date_added_ts":"1295881220","view_count":"13","attachment":"http:\/\/wwwdup.uni-leipzig.de\/jobportal\/job\/download\/396.pdf"}