{"id":"529","title":"Junior Consultant Analytics (w\/m) ","description":"*Das Unternehmen:* \r\nb.telligent ist eine Unternehmensberatung, die auf Einf\u00fchrung und Weiterentwicklung von \r\nBusiness Intelligence in Unternehmen in Massenm\u00e4rkten spezialisiert ist. Business Intelligence \r\ndient der Optimierung von Gesch\u00e4ftsprozessen, Kunden- und Lieferantenbeziehungen durch den \r\nErkenntnisgewinn aus der Verarbeitung und Analyse von \u00fcbergreifenden Gesch\u00e4ftsdaten. So \r\nlassen sich Margen erh\u00f6hen, Kosten senken und Risiken besser kontrollieren. Kunden von \r\nb.telligent sind europ\u00e4ische Branchenf\u00fchrer in Telekommunikation, Finanzdienstleistung und \r\nHandel. \r\n \r\nF\u00fcr unser B\u00fcro in M\u00fcnchen suchen wir zum n\u00e4chstm\u00f6glichen Zeitpunkt einen Junior Consultant \r\nAnalytics (w\/m) zur Festanstellung. \r\n \r\n \r\n*Ihre Aufgaben:* \r\n \r\n*Auswertung kundenbezogener Daten mit Hilfe von Oracle SQL oder PL\/SQL  \r\n*Durchf\u00fchrung deskriptiver und explorativer Analysen mit SAS, SPSS oder R \r\n*Klassifizierung von Kunden und Durchf\u00fchrung von Kundenstrukturanalysen \r\n*Entwicklung von statistischen Prognosemodellen \r\n \r\n \r\n \r\n*Ihre Qualifikationen:*\r\n \r\n*\u00dcberdurchschnittlich abgeschlossenes Studium der Mathematik oder Statistik oder der \r\nWirtschaftsinformatik, Informatik, Betriebswirtschaftslehre mit Schwerpunkt IT \r\n*Hervorragende Kommunikationsf\u00e4higkeiten in Deutsch und Englisch \r\n*Praktische Erfahrungen mit SQL \r\n*Kenntnisse im Umgang mit Datenbanken und Daten, vorzugsweise Oracle \r\n*Idealerweise Erfahrungen mit R oder Softwaremodulen von SAS \r\n*Leistungs- und Lernbereitschaft \r\n \r\n \r\n*Welcome!* Lernen Sie uns kennen und erz\u00e4hlen Sie uns Ihre Erfolgsgeschichte.  \r\nBitte  senden  Sie  Ihre  aussagekr\u00e4ftigen  Bewerbungsunterlagen,  Ihren  Starttermin  und  Ihre \r\nGehaltsvorstellung an: \r\n \r\n \r\n*b.telligent* GmbH & Co. KG \r\nMareike Schumacher \r\nUptown M\u00fcnchen Campus D \r\nGeorg-Brauchle-Ring 60 \r\n80992 M\u00fcnchen \r\n \r\noder per E-Mail an recruiting@btelligent.com ","how_to_apply":"per e-mail oder per Post","company":"b.telligent","company_homepage":"http:\/\/www.btelligent.com ","zipcode":"80992","city":"M\u00fcnchen","state":"Bayern","country":"Deutschland","job_version":"1","expiration_date":"28.03.2011","expiration_date_ts":"1301263200","date_added":"14.02.2011","date_added_ts":"1297680051","view_count":"17","attachment":"http:\/\/wwwdup.uni-leipzig.de\/jobportal\/job\/download\/529.pdf"}