{"id":"767","title":"Praktikum im Produktmanagement f\u00fcr polnische Muttersprachlehrer","description":"Mach Urlaub zu deinem Beruf! Die SOLEGRO GmbH mit Sitz in Hamburg betreibt als Touristikunternehmen die Onlinereiseportale www.solegro.de sowie www.lloretdemar.de und z\u00e4hlt zu den f\u00fchrenden veranstalterunabh\u00e4ngigen Jugendreiseportalen. Wir b\u00fcndeln die Angebote zahlreicher namhafter Veranstalter und bieten eine breite Produktpalette von Sommer-, Ski-, Abi-, St\u00e4dte-, Event-, Sprach- und Sportreisen. F\u00fcr die Verst\u00e4rkung unseres jungen polnischen Teams bieten wir dir einen verg\u00fcteten Praktikumsplatz im Bereich Produktmanagement an.Stellenbeschreibung:Du unterst\u00fctzt das Team im Produktmanagement, pr\u00fcfst und \u00e4nderst die Top-Angebote auf unseren Webseiten, erweiterst unser Produktportfolio, beantwortest Kundenanfragen und erarbeitest Handlungsoptionen f\u00fcr den weiteren Ausbau im Wachstumsmarkt Jugendreisen. Hier lernst du das Arbeiten mit Content Management Systemen, erh\u00e4ltst die Gelegenheit t\u00e4glich neue, eigene Ideen einzu-bringen und gewinnst Einblicke in den Online-Reisemarkt. Die freundliche und zielgerichtete Arbeitsatmosph\u00e4re zeichnet das Unternehmen aus.Dein Profil:- Du studierst Touristik, BWL o.\u00e4.- Du hast sehr gute PC-Kenntnisse und bist internetaffin- Du sprichst\/schreibst sehr gut Polnisch (Muttersprache)- Du bist kommunikativ und hast gute Deutschkenntnisse- Du arbeitest selbst\u00e4ndig und eigenverantwortlich- Du bist motiviert, flexibel und zielorientiert- Du interessierst dich f\u00fcr Reisen und TouristikHaben wir dein Interesse geweckt? Dann lass uns deine Bewerbungsunterlagen per E-Mail zukommen an bewerbung@solegro.de. Wir freuen uns darauf dich kennenzulernen.","how_to_apply":null,"company":"SOLEGRO","company_homepage":"http:\/\/www.solegro.de","zipcode":"20354","city":"Hamburg","state":null,"country":null,"job_version":"2","expiration_date":"29.04.2011","expiration_date_ts":"1304028000","date_added":"18.03.2011","date_added_ts":"1300446896","view_count":"33"}