{"id":"812","title":"Italienische Muttersprachler f\u00fcr Online Marketing gesucht","description":"\t\tDREAMLINES.de ist das neue Kreuzfahrtportal. Unsere<br>Produktpalette umfasst klassische Hochseekreuzfahrten,<br>Clubschiffe, Flussreisen und Segelschifffahrten. Schon bald wird<br>hier jeder Kunde seine Traumreise auf See finden.<br>Wir wachsen weiter und suchen Verst\u00e4rkung f\u00fcr unser junges<br>italienisches Team im Bereich Online Marketing.<br><br><br>Ihre Aufgaben<br>- Unterst\u00fctzung des Team in der Planung zur Verkaufsf\u00f6rderung<br>- eigene Projekte aus dem Bereich SEO<br>- Arbeit mit Content Management Systemen<br>- allt\u00e4gliche Aufgaben aus dem Online Marketing<br><br>Ihre Qualifikationen<br>- Sie studieren Tourismus, BWL, o.\u00e4.<br>- Sie haben sehr gute PC-Kenntnisse, sind internetaffin<br>- Sie schreiben\/sprechen sehr gut Italienisch (Muttersprache)<br>- Sie sind sprechen gut Deutsch<br>- Sie arbeiten gerne selbst\u00e4ndig<br><br>Wir bieten Ihnen 500 \u2013 700 \u20ac pro Monat, einen Arbeitsplatz im<br>Zentrum von Hamburg, ein junges hochmotiviertes Team von Ecommerce<br>Spezialisten, eine freundlich und zielgerichtete<br>Arbeitsatmosph\u00e4re, die Gelegenheit den Online Reisemarkt<br>kennen zu lernen und t\u00e4glich eigene, neue Ideen einzubringen.<br>Konnten wir Sie begeistern? Dann bewerben Sie sich noch<br>heute unter bewerbung@dreamlines.de.<br><br>\t<br><br><br><br>","how_to_apply":null,"company":"dreamlines.de","company_homepage":"http:\/\/www.dreamlines.de","zipcode":"20354","city":"Hamburg","state":null,"country":null,"job_version":"2","expiration_date":"06.05.2011","expiration_date_ts":"1304632800","date_added":"25.03.2011","date_added_ts":"1301048203","view_count":"8"}