{"id":"855","title":"LOTUM GmbH Praktikum HR Marketing Assistant","description":"<br><br><em><\/em>Wir suchen ...<p>einen\r\n Praktikanten (m\/w) im Bereich Personalmarketing \/ Talent Acquisition, \r\nder potentielle Kandidaten f\u00fcr uns begeistert und Recruiting 2.0 sowie \r\nEmployer Branding spannend findet.<\/p>Fakten zum Praktikum<p>Der Beginn des verg\u00fcteten Praktikums ist ab sofort m\u00f6glich. Die Dauer des Praktikums sollte 3 bis 6 Monate betragen.<\/p><p><br><\/p><p><br><\/p><div>Dein Profil ...<p><strong>Zielgruppen ansprechen. <\/strong>Du kannst dich problemlos in die anvisierte Zielgruppe hineinversetzen und sie pr\u00e4zise erreichen.<\/p><p><strong>Textkompetenz. <\/strong>Du verf\u00fcgst \u00fcber sichere Rechtsschreibung, guten Ausdruck und Stil. <\/p><p><strong>Office. <\/strong>Du kennst dich sehr gut mit Microsofts Office-Paket aus, insbesondere Excel.<\/p><p><strong>Organisationstalent. <\/strong>Als\r\n Ansprechpartner f\u00fcr Mitarbeiter verschiedenster Bereiche beh\u00e4ltst du \r\nden \u00dcberblick \u00fcber deine Aufgaben und erledigst diese flexibel und \r\neigeninitiativ. <\/p><p><strong>Analytische F\u00e4higkeiten. <\/strong>Du hast ein gutes Gesp\u00fcr f\u00fcr Zahlen, Relationen und Kausalit\u00e4ten.<\/p><p><strong>Web 2.0 und Social Media. <\/strong>Du bist fasziniert von den M\u00f6glichkeiten sozialer Interaktion im Netz.<\/p><p><br><\/p><p><br><\/p><div>Wir bieten ...<p><strong>Relevanz.<\/strong>\r\n Keine theoretischen \u00dcberlegungen und Ideen f\u00fcr den Papierkorb. Auf \r\ndeine Personalmarketing-Aktionen von heute antworten schon morgen die \r\nersten Bewerber.<\/p><p><strong>Atmosph\u00e4re.<\/strong> In einem jungen und sympathischen Unternehmen genie\u00dft du eine kollegial-freundschaftliche Atmosph\u00e4re, die ihresgleichen sucht.<\/p><p><strong>Herausforderung.<\/strong>\r\n Deine Aufgaben und Ziele verlangen dir einiges ab. Du wirst permanent \r\nmit neuen Herausforderungen konfrontiert, dabei aber nie alleine \r\ngelassen.<\/p><p><strong>Innovation.<\/strong> \r\nSchreite mit uns abseits der ausgetretenen Recruiting-Pfade. Jede gute \r\nIdee wird schnellstm\u00f6glich umgesetzt \u2013 egal von wem sie stammt.<\/p><p><strong>Freiraum<\/strong> Kreativit\u00e4t und Eigenverantwortlichkeit f\u00fcr deine pers\u00f6nliche wie berufliche Entwicklung.<\/p>Dein Arbeitsfeld<p>Dein\r\n Ziel ist es, den Recruiting-Prozess mit allen Mitteln zu unterst\u00fctzen, \r\nneue Mitarbeiter zu gewinnen und unsere Attraktivit\u00e4t als Arbeitsgeber \r\nzu erh\u00f6hen. Du k\u00fcmmerst dich um die Planung, Durchf\u00fchrung und \r\nEvaluierung von Personalmarketing-Ma\u00dfnahmen. Dazu geh\u00f6ren unter anderem \r\ndas Texten von Stellenbeschreibungen, Online- und Printanzeigen, das \r\nBearbeiten eingehender Bewerbungen und die direkte Ansprache passiver \r\nKandidaten. Zudem k\u00fcmmerst du dich um unseren Blog und weitere \r\nSocial-Media-Projekte.<\/p><p>Wenn all dies deinen Interessen und \r\nErwartungen entspricht und du uns mit viel Engagement unterst\u00fctzen \r\nm\u00f6chtest, dann w\u00fcrden wir uns sehr freuen, wenn du uns deine \r\naussagekr\u00e4ftige Bewerbung (Referenzen, Lebenslauf, Zeugnisse) mit Angabe\r\n deiner zeitlichen Verf\u00fcgbarkeit und Gehaltsvorstellung zukommen l\u00e4sst.<\/p><br><br><\/div><\/div>Bewerbung<strong><br>Per E-Mail: (bevorzugt)<\/strong> bewerbung [at] lotum.de<br><strong>Postanschrift<\/strong>LOTUM GmbH<br>Julia Schmidt<br>Kurstra\u00dfe 2<br>61231 Bad Nauheim<br><br>\t<br><br><br><br><br><br><br><br>","how_to_apply":null,"company":"LOTUM GmbH","company_homepage":"http:\/\/www.lotum.de","zipcode":"61231","city":"Bad Nauheim","state":null,"country":null,"job_version":"2","expiration_date":"12.05.2011","expiration_date_ts":"1305151200","date_added":"31.03.2011","date_added_ts":"1301561817","view_count":"6"}